click_expand/__init__.py
click_expand/__main__.py
click_expand/expand.py
click_expand-0.1.0.dist-info/entry_points.txt
click_expand-0.1.0.dist-info/licenses/LICENSE
click_expand-0.1.0.dist-info/WHEEL
click_expand-0.1.0.dist-info/METADATA
click_expand-0.1.0.dist-info/RECORD
