Metadata-Version: 2.4
Name: click_expand
Version: 0.1.0
Summary: Generate click group and command skeletons from simple comments.
Author-email: jamerfort <jamerfort+pypi@gmail.com>
License-Expression: MIT
License-File: LICENSE
